bgvirtualstocks/AutoDashFinalV2.py
bgvirtualstocks/__init__.py
bgvirtualstocks-0.0.1.dist-info/METADATA
bgvirtualstocks-0.0.1.dist-info/RECORD
bgvirtualstocks-0.0.1.dist-info/WHEEL
bgvirtualstocks-0.0.1.dist-info/top_level.txt
