Metadata-Version: 2.1
Name: bgvirtualstocks
Version: 0.0.1
Summary: An automated stock trading virtual environment via google sheets.
Home-page: https://github.com/
Author: Brendan Greenlee
Author-email: greenlbt@miamioh.edu
License: UNKNOWN
Platform: UNKNOWN
Classifier: Programming Language :: Python :: 3
Classifier: License :: OSI Approved :: MIT License
Classifier: Operating System :: OS Independent
